[
  {
    "title": "Web Development",
    "description": "A complete website build for small businesses and personal brands.",
    "price": "Starting at $750",
    "icon": "Web",
    "value": "web-development"
  },
  {
    "title": "Accessibility Audit & Fixes",
    "description": "Audit + prioritized fixes to improve accessibility and reduce risk.",
    "price": "Starting at $600",
    "icon": "Accessibility",
    "value": "accessibility-audit"
  },
  {
    "title": "SEO Audit & Optimization",
    "description": "Audit + keyword direction + on-page improvements for search growth.",
    "price": "Starting at $500",
    "icon": "Search",
    "value": "seo-audit"
  },
  {
    "title": "UX Improvements",
    "description": "Improve clarity and conversions with layout, copy, and flow updates.",
    "price": "Starting at $450",
    "icon": "DesignServices",
    "value": "ux-improvements"
  },
  {
    "title": "SQL & ETL Consulting",
    "description": "SQL optimization, migrations, ETL, reporting, and database integrations.",
    "price": "Starting at $550",
    "icon": "Storage",
    "value": "sql-etl"
  },
  {
    "title": "Excel Analytics & Automation",
    "description": "Dashboards and automation to turn spreadsheets into decision tools.",
    "price": "Starting at $400",
    "icon": "BarChart",
    "value": "excel-analytics"
  },
  {
    "title": "Maintenance & Support",
    "description": "Ongoing updates, fixes, and performance checks to keep your site healthy.",
    "price": "$99–$299/month",
    "icon": "Support",
    "value": "maintenance-support"
  }
]
